[
    {
        "filename": "output_photo_map\\img_0_0.png",
        "x": -100.0,
        "y": -16.5
    },
    {
        "filename": "output_photo_map\\img_0_1.png",
        "x": -100.0,
        "y": -12.922222222222222
    },
    {
        "filename": "output_photo_map\\img_0_2.png",
        "x": -100.0,
        "y": -9.344444444444445
    },
    {
        "filename": "output_photo_map\\img_0_3.png",
        "x": -100.0,
        "y": -5.766666666666666
    },
    {
        "filename": "output_photo_map\\img_0_4.png",
        "x": -100.0,
        "y": -2.188888888888888
    },
    {
        "filename": "output_photo_map\\img_0_5.png",
        "x": -100.0,
        "y": 1.3888888888888893
    },
    {
        "filename": "output_photo_map\\img_0_6.png",
        "x": -100.0,
        "y": 4.966666666666669
    },
    {
        "filename": "output_photo_map\\img_0_7.png",
        "x": -100.0,
        "y": 8.544444444444444
    },
    {
        "filename": "output_photo_map\\img_0_8.png",
        "x": -100.0,
        "y": 12.122222222222224
    },
    {
        "filename": "output_photo_map\\img_0_9.png",
        "x": -100.0,
        "y": 15.700000000000003
    },
    {
        "filename": "output_photo_map\\img_1_0.png",
        "x": -90.24444444444444,
        "y": -16.5
    },
    {
        "filename": "output_photo_map\\img_1_1.png",
        "x": -90.24444444444444,
        "y": -12.922222222222222
    },
    {
        "filename": "output_photo_map\\img_1_2.png",
        "x": -90.24444444444444,
        "y": -9.344444444444445
    },
    {
        "filename": "output_photo_map\\img_1_3.png",
        "x": -90.24444444444444,
        "y": -5.766666666666666
    },
    {
        "filename": "output_photo_map\\img_1_4.png",
        "x": -90.24444444444444,
        "y": -2.188888888888888
    },
    {
        "filename": "output_photo_map\\img_1_5.png",
        "x": -90.24444444444444,
        "y": 1.3888888888888893
    },
    {
        "filename": "output_photo_map\\img_1_6.png",
        "x": -90.24444444444444,
        "y": 4.966666666666669
    },
    {
        "filename": "output_photo_map\\img_1_7.png",
        "x": -90.24444444444444,
        "y": 8.544444444444444
    },
    {
        "filename": "output_photo_map\\img_1_8.png",
        "x": -90.24444444444444,
        "y": 12.122222222222224
    },
    {
        "filename": "output_photo_map\\img_1_9.png",
        "x": -90.24444444444444,
        "y": 15.700000000000003
    },
    {
        "filename": "output_photo_map\\img_2_0.png",
        "x": -80.4888888888889,
        "y": -16.5
    },
    {
        "filename": "output_photo_map\\img_2_1.png",
        "x": -80.4888888888889,
        "y": -12.922222222222222
    },
    {
        "filename": "output_photo_map\\img_2_2.png",
        "x": -80.4888888888889,
        "y": -9.344444444444445
    },
    {
        "filename": "output_photo_map\\img_2_3.png",
        "x": -80.4888888888889,
        "y": -5.766666666666666
    },
    {
        "filename": "output_photo_map\\img_2_4.png",
        "x": -80.4888888888889,
        "y": -2.188888888888888
    },
    {
        "filename": "output_photo_map\\img_2_5.png",
        "x": -80.4888888888889,
        "y": 1.3888888888888893
    },
    {
        "filename": "output_photo_map\\img_2_6.png",
        "x": -80.4888888888889,
        "y": 4.966666666666669
    },
    {
        "filename": "output_photo_map\\img_2_7.png",
        "x": -80.4888888888889,
        "y": 8.544444444444444
    },
    {
        "filename": "output_photo_map\\img_2_8.png",
        "x": -80.4888888888889,
        "y": 12.122222222222224
    },
    {
        "filename": "output_photo_map\\img_2_9.png",
        "x": -80.4888888888889,
        "y": 15.700000000000003
    },
    {
        "filename": "output_photo_map\\img_3_0.png",
        "x": -70.73333333333333,
        "y": -16.5
    },
    {
        "filename": "output_photo_map\\img_3_1.png",
        "x": -70.73333333333333,
        "y": -12.922222222222222
    },
    {
        "filename": "output_photo_map\\img_3_2.png",
        "x": -70.73333333333333,
        "y": -9.344444444444445
    },
    {
        "filename": "output_photo_map\\img_3_3.png",
        "x": -70.73333333333333,
        "y": -5.766666666666666
    },
    {
        "filename": "output_photo_map\\img_3_4.png",
        "x": -70.73333333333333,
        "y": -2.188888888888888
    },
    {
        "filename": "output_photo_map\\img_3_5.png",
        "x": -70.73333333333333,
        "y": 1.3888888888888893
    },
    {
        "filename": "output_photo_map\\img_3_6.png",
        "x": -70.73333333333333,
        "y": 4.966666666666669
    },
    {
        "filename": "output_photo_map\\img_3_7.png",
        "x": -70.73333333333333,
        "y": 8.544444444444444
    },
    {
        "filename": "output_photo_map\\img_3_8.png",
        "x": -70.73333333333333,
        "y": 12.122222222222224
    },
    {
        "filename": "output_photo_map\\img_3_9.png",
        "x": -70.73333333333333,
        "y": 15.700000000000003
    },
    {
        "filename": "output_photo_map\\img_4_0.png",
        "x": -60.97777777777778,
        "y": -16.5
    },
    {
        "filename": "output_photo_map\\img_4_1.png",
        "x": -60.97777777777778,
        "y": -12.922222222222222
    },
    {
        "filename": "output_photo_map\\img_4_2.png",
        "x": -60.97777777777778,
        "y": -9.344444444444445
    },
    {
        "filename": "output_photo_map\\img_4_3.png",
        "x": -60.97777777777778,
        "y": -5.766666666666666
    },
    {
        "filename": "output_photo_map\\img_4_4.png",
        "x": -60.97777777777778,
        "y": -2.188888888888888
    },
    {
        "filename": "output_photo_map\\img_4_5.png",
        "x": -60.97777777777778,
        "y": 1.3888888888888893
    },
    {
        "filename": "output_photo_map\\img_4_6.png",
        "x": -60.97777777777778,
        "y": 4.966666666666669
    },
    {
        "filename": "output_photo_map\\img_4_7.png",
        "x": -60.97777777777778,
        "y": 8.544444444444444
    },
    {
        "filename": "output_photo_map\\img_4_8.png",
        "x": -60.97777777777778,
        "y": 12.122222222222224
    },
    {
        "filename": "output_photo_map\\img_4_9.png",
        "x": -60.97777777777778,
        "y": 15.700000000000003
    },
    {
        "filename": "output_photo_map\\img_5_0.png",
        "x": -51.22222222222223,
        "y": -16.5
    },
    {
        "filename": "output_photo_map\\img_5_1.png",
        "x": -51.22222222222223,
        "y": -12.922222222222222
    },
    {
        "filename": "output_photo_map\\img_5_2.png",
        "x": -51.22222222222223,
        "y": -9.344444444444445
    },
    {
        "filename": "output_photo_map\\img_5_3.png",
        "x": -51.22222222222223,
        "y": -5.766666666666666
    },
    {
        "filename": "output_photo_map\\img_5_4.png",
        "x": -51.22222222222223,
        "y": -2.188888888888888
    },
    {
        "filename": "output_photo_map\\img_5_5.png",
        "x": -51.22222222222223,
        "y": 1.3888888888888893
    },
    {
        "filename": "output_photo_map\\img_5_6.png",
        "x": -51.22222222222223,
        "y": 4.966666666666669
    },
    {
        "filename": "output_photo_map\\img_5_7.png",
        "x": -51.22222222222223,
        "y": 8.544444444444444
    },
    {
        "filename": "output_photo_map\\img_5_8.png",
        "x": -51.22222222222223,
        "y": 12.122222222222224
    },
    {
        "filename": "output_photo_map\\img_5_9.png",
        "x": -51.22222222222223,
        "y": 15.700000000000003
    },
    {
        "filename": "output_photo_map\\img_6_0.png",
        "x": -41.46666666666667,
        "y": -16.5
    },
    {
        "filename": "output_photo_map\\img_6_1.png",
        "x": -41.46666666666667,
        "y": -12.922222222222222
    },
    {
        "filename": "output_photo_map\\img_6_2.png",
        "x": -41.46666666666667,
        "y": -9.344444444444445
    },
    {
        "filename": "output_photo_map\\img_6_3.png",
        "x": -41.46666666666667,
        "y": -5.766666666666666
    },
    {
        "filename": "output_photo_map\\img_6_4.png",
        "x": -41.46666666666667,
        "y": -2.188888888888888
    },
    {
        "filename": "output_photo_map\\img_6_5.png",
        "x": -41.46666666666667,
        "y": 1.3888888888888893
    },
    {
        "filename": "output_photo_map\\img_6_6.png",
        "x": -41.46666666666667,
        "y": 4.966666666666669
    },
    {
        "filename": "output_photo_map\\img_6_7.png",
        "x": -41.46666666666667,
        "y": 8.544444444444444
    },
    {
        "filename": "output_photo_map\\img_6_8.png",
        "x": -41.46666666666667,
        "y": 12.122222222222224
    },
    {
        "filename": "output_photo_map\\img_6_9.png",
        "x": -41.46666666666667,
        "y": 15.700000000000003
    },
    {
        "filename": "output_photo_map\\img_7_0.png",
        "x": -31.711111111111123,
        "y": -16.5
    },
    {
        "filename": "output_photo_map\\img_7_1.png",
        "x": -31.711111111111123,
        "y": -12.922222222222222
    },
    {
        "filename": "output_photo_map\\img_7_2.png",
        "x": -31.711111111111123,
        "y": -9.344444444444445
    },
    {
        "filename": "output_photo_map\\img_7_3.png",
        "x": -31.711111111111123,
        "y": -5.766666666666666
    },
    {
        "filename": "output_photo_map\\img_7_4.png",
        "x": -31.711111111111123,
        "y": -2.188888888888888
    },
    {
        "filename": "output_photo_map\\img_7_5.png",
        "x": -31.711111111111123,
        "y": 1.3888888888888893
    },
    {
        "filename": "output_photo_map\\img_7_6.png",
        "x": -31.711111111111123,
        "y": 4.966666666666669
    },
    {
        "filename": "output_photo_map\\img_7_7.png",
        "x": -31.711111111111123,
        "y": 8.544444444444444
    },
    {
        "filename": "output_photo_map\\img_7_8.png",
        "x": -31.711111111111123,
        "y": 12.122222222222224
    },
    {
        "filename": "output_photo_map\\img_7_9.png",
        "x": -31.711111111111123,
        "y": 15.700000000000003
    },
    {
        "filename": "output_photo_map\\img_8_0.png",
        "x": -21.955555555555563,
        "y": -16.5
    },
    {
        "filename": "output_photo_map\\img_8_1.png",
        "x": -21.955555555555563,
        "y": -12.922222222222222
    },
    {
        "filename": "output_photo_map\\img_8_2.png",
        "x": -21.955555555555563,
        "y": -9.344444444444445
    },
    {
        "filename": "output_photo_map\\img_8_3.png",
        "x": -21.955555555555563,
        "y": -5.766666666666666
    },
    {
        "filename": "output_photo_map\\img_8_4.png",
        "x": -21.955555555555563,
        "y": -2.188888888888888
    },
    {
        "filename": "output_photo_map\\img_8_5.png",
        "x": -21.955555555555563,
        "y": 1.3888888888888893
    },
    {
        "filename": "output_photo_map\\img_8_6.png",
        "x": -21.955555555555563,
        "y": 4.966666666666669
    },
    {
        "filename": "output_photo_map\\img_8_7.png",
        "x": -21.955555555555563,
        "y": 8.544444444444444
    },
    {
        "filename": "output_photo_map\\img_8_8.png",
        "x": -21.955555555555563,
        "y": 12.122222222222224
    },
    {
        "filename": "output_photo_map\\img_8_9.png",
        "x": -21.955555555555563,
        "y": 15.700000000000003
    },
    {
        "filename": "output_photo_map\\img_9_0.png",
        "x": -12.200000000000003,
        "y": -16.5
    },
    {
        "filename": "output_photo_map\\img_9_1.png",
        "x": -12.200000000000003,
        "y": -12.922222222222222
    },
    {
        "filename": "output_photo_map\\img_9_2.png",
        "x": -12.200000000000003,
        "y": -9.344444444444445
    },
    {
        "filename": "output_photo_map\\img_9_3.png",
        "x": -12.200000000000003,
        "y": -5.766666666666666
    },
    {
        "filename": "output_photo_map\\img_9_4.png",
        "x": -12.200000000000003,
        "y": -2.188888888888888
    },
    {
        "filename": "output_photo_map\\img_9_5.png",
        "x": -12.200000000000003,
        "y": 1.3888888888888893
    },
    {
        "filename": "output_photo_map\\img_9_6.png",
        "x": -12.200000000000003,
        "y": 4.966666666666669
    },
    {
        "filename": "output_photo_map\\img_9_7.png",
        "x": -12.200000000000003,
        "y": 8.544444444444444
    },
    {
        "filename": "output_photo_map\\img_9_8.png",
        "x": -12.200000000000003,
        "y": 12.122222222222224
    },
    {
        "filename": "output_photo_map\\img_9_9.png",
        "x": -12.200000000000003,
        "y": 15.700000000000003
    }
]